cpp_symbol_parser-0.1.2.dist-info/METADATA
cpp_symbol_parser-0.1.2.dist-info/WHEEL
cpp_symbol_parser/__init__.py
cpp_symbol_parser/ast.py
cpp_symbol_parser/grammar.lark
cpp_symbol_parser/parser.py
cpp_symbol_parser/transform.py
cpp_symbol_parser-0.1.2.dist-info/RECORD
