Metadata-Version: 2.1
Name: cpp-symbol-parser
Version: 0.1.2
Summary: Parser for mangled C++ symbols
Author-Email: Vegard Storheil Eriksen <zyp@jvnv.net>
License: MIT
Requires-Python: >=3.10
Requires-Dist: lark>=1.1.9
